LICENSE
MANIFEST.in
README.rst
pytest_ry_demo.py
setup.py
pytest_ry_demo1.egg-info/PKG-INFO
pytest_ry_demo1.egg-info/SOURCES.txt
pytest_ry_demo1.egg-info/dependency_links.txt
pytest_ry_demo1.egg-info/entry_points.txt
pytest_ry_demo1.egg-info/requires.txt
pytest_ry_demo1.egg-info/top_level.txt