Metadata-Version: 2.1
Name: pytest-ry-demo1
Version: 0.1.0
Summary: 测试
Home-page: https://github.com/ryhn0412/pytest-ry_demo
Author: ryhn
Author-email: xuehy@tomtaw.com.cn
Maintainer: ryhn
Maintainer-email: xuehy@tomtaw.com.cn
License: BSD-3
Platform: UNKNOWN
Requires-Python: >=3.8
License-File: LICENSE
